mastodon_reader/__init__.py
mastodon_reader/mastodon_reader.py
mastodon_reader/utils.py
mastodon_reader/version.py
Mastodon_Reader-0.3.1.dist-info/LICENSE
Mastodon_Reader-0.3.1.dist-info/METADATA
Mastodon_Reader-0.3.1.dist-info/WHEEL
Mastodon_Reader-0.3.1.dist-info/top_level.txt
Mastodon_Reader-0.3.1.dist-info/RECORD
