Metadata-Version: 2.1
Name: Mastodon-Reader
Version: 0.3.1
Summary: Mastodon project file reader for Python
Home-page: https://git.ist.ac.at/csommer/mastodon_reader
Author: Christoph Sommer
Author-email: christoph.sommer23@gmail.com
License: BSD
Classifier: Development Status :: 4 - Beta
Classifier: Programming Language :: Python :: 3
Classifier: License :: OSI Approved :: BSD License
License-File: LICENSE
Requires-Dist: numpy
Requires-Dist: pandas
Requires-Dist: networkx
